[{"buildOrder":26,"reportUrl":"https://robyrakesh.github.io/Autodesk/26/","reportName":"Allure Report with history","data":{"duration":519769}},{"buildOrder":25,"reportUrl":"https://robyrakesh.github.io/Autodesk/25/","reportName":"Allure Report with history","data":{"duration":519724}},{"buildOrder":24,"reportUrl":"https://robyrakesh.github.io/Autodesk/24/","reportName":"Allure Report with history","data":{"duration":512868}},{"buildOrder":23,"reportUrl":"https://robyrakesh.github.io/Autodesk/23/","reportName":"Allure Report with history","data":{"duration":512587}},{"buildOrder":22,"reportUrl":"https://robyrakesh.github.io/Autodesk/22/","reportName":"Allure Report with history","data":{"duration":513011}},{"data":{}}]